safetydance_test/__init__.py
safetydance_test/step_extension.py
safetydance_test-0.2.0.dist-info/LICENSE.txt
safetydance_test-0.2.0.dist-info/WHEEL
safetydance_test-0.2.0.dist-info/METADATA
safetydance_test-0.2.0.dist-info/RECORD
