Metadata-Version: 2.1
Name: safetydance-test
Version: 0.2.0
Summary: A testing framework built upon the typesafe composition of steps.
Home-page: https://github.com/dcharbon/safetydance_test
License: MIT
Author: David Charboneau
Author-email: david@adadabase.com
Requires-Python: >=3.7,<4.0
Classifier: License :: OSI Approved :: MIT License
Classifier: Programming Language :: Python :: 3
Classifier: Programming Language :: Python :: 3.10
Classifier: Programming Language :: Python :: 3.7
Classifier: Programming Language :: Python :: 3.8
Classifier: Programming Language :: Python :: 3.9
Requires-Dist: pytest (>=6.2.2,<7.0.0)
Requires-Dist: safetydance (>=0.3.1,<0.4.0)
Requires-Dist: type-extensions (>=0.1.2,<0.2.0)
Project-URL: Repository, https://github.com/dcharbon/safetydance_test.git
